lib_missing_people_api/__init__.py
lib_missing_people_api/models.py
lib_missing_people_api/parser.py
lib_missing_people_api-1.0.dist-info/METADATA
lib_missing_people_api-1.0.dist-info/WHEEL
lib_missing_people_api-1.0.dist-info/top_level.txt
lib_missing_people_api-1.0.dist-info/RECORD
