Metadata-Version: 2.4
Name: lib_missing_people_api
Version: 1.0
Summary: Library-api for scrapping missing people
Home-page: https://github.com/YuranIgnatenko/lib_missing_people_api
Author: Yurij
Author-email: yuran.ignatenko@yander.ru
Requires-Dist: requests
Requires-Dist: beautifulsoup4
Requires-Dist: fake_useragent
Dynamic: author
Dynamic: author-email
Dynamic: description
Dynamic: description-content-type
Dynamic: home-page
Dynamic: requires-dist
Dynamic: summary
